rustproj/__init__.py
rustproj/proj_generator.py
rustproj/run.py
rustproj-0.1.1.dist-info/LICENSE
rustproj-0.1.1.dist-info/METADATA
rustproj-0.1.1.dist-info/WHEEL
rustproj-0.1.1.dist-info/entry_points.txt
rustproj-0.1.1.dist-info/top_level.txt
rustproj-0.1.1.dist-info/RECORD
