Metadata-Version: 2.1
Name: rustproj
Version: 0.1.1
Summary: Simple rust project generator
Home-page: https://github.com/frankhart2018/rustproj
Author: Siddhartha Dhar Choudhury
Author-email: sdharchou@gmail.com
License: MIT
Platform: UNKNOWN
Classifier: License :: OSI Approved :: MIT License
Classifier: Programming Language :: Python :: 3
Classifier: Programming Language :: Python :: 3.9
Classifier: Programming Language :: Python :: 3.8
Classifier: Programming Language :: Python :: 3.7
Classifier: Programming Language :: Python :: 3.6
